messaging_arbihacker/__init__.py
messaging_arbihacker-0.1.10.dist-info/METADATA
messaging_arbihacker-0.1.10.dist-info/WHEEL
messaging_arbihacker-0.1.10.dist-info/licenses/LICENSE
messaging_arbihacker-0.1.10.dist-info/RECORD
